pysherplus/__init__.py
pysherplus/authentication.py
pysherplus/channel.py
pysherplus/connection.py
pysherplus/pusher.py
PysherPlus-2.0.1.dist-info/LICENSE
PysherPlus-2.0.1.dist-info/METADATA
PysherPlus-2.0.1.dist-info/WHEEL
PysherPlus-2.0.1.dist-info/top_level.txt
PysherPlus-2.0.1.dist-info/RECORD
