Metadata-Version: 2.1
Name: PysherPlus
Version: 2.0.1
Summary: Pusher websocket client for python, based on deepbrook's fork of Erik Kulyk's PythonPusherClient
Home-page: https://github.com/jnesselr/PysherPlus
Author: Justin Nesselrotte
Author-email: admin@jnesselr.org
License: MIT
Keywords: pusher websocket client
Platform: UNKNOWN
Classifier: Development Status :: 4 - Beta
Classifier: Environment :: Web Environment
Classifier: License :: OSI Approved :: MIT License
Classifier: Programming Language :: Python
Classifier: Programming Language :: Python :: 3.5
Classifier: Programming Language :: Python :: 3.6
Classifier: Programming Language :: Python :: 3.7
Classifier: Topic :: Internet
Classifier: Topic :: Software Development :: Libraries 
Classifier: Topic :: Software Development :: Libraries :: Python Modules
License-File: LICENSE
Requires-Dist: websocket-client
Requires-Dist: requests
